odoo/addons/report_display_name_in_footer/README.rst
odoo/addons/report_display_name_in_footer/__init__.py
odoo/addons/report_display_name_in_footer/__manifest__.py
odoo/addons/report_display_name_in_footer/data/report_data.xml
odoo/addons/report_display_name_in_footer/i18n/it.po
odoo/addons/report_display_name_in_footer/i18n/report_display_name_in_footer.pot
odoo/addons/report_display_name_in_footer/models/__init__.py
odoo/addons/report_display_name_in_footer/models/ir_actions_report.py
odoo/addons/report_display_name_in_footer/readme/CONFIGURE.md
odoo/addons/report_display_name_in_footer/readme/CONTEXT.md
odoo/addons/report_display_name_in_footer/readme/CONTRIBUTORS.md
odoo/addons/report_display_name_in_footer/readme/DESCRIPTION.md
odoo/addons/report_display_name_in_footer/readme/ROADMAP.md
odoo/addons/report_display_name_in_footer/readme/USAGE.md
odoo/addons/report_display_name_in_footer/static/description/icon.png
odoo/addons/report_display_name_in_footer/static/description/index.html
odoo/addons/report_display_name_in_footer/views/report_templates.xml
odoo_addon_report_display_name_in_footer-16.0.1.1.0.dist-info/METADATA
odoo_addon_report_display_name_in_footer-16.0.1.1.0.dist-info/WHEEL
odoo_addon_report_display_name_in_footer-16.0.1.1.0.dist-info/top_level.txt
odoo_addon_report_display_name_in_footer-16.0.1.1.0.dist-info/RECORD
